pyMolinfo/__init__.py
pyMolinfo/app.py
pyMolinfo/config/__init__.py
pyMolinfo/config/constants.py
pyMolinfo/config/setting.py
pyMolinfo/data/__init__.py
pyMolinfo/docs/__init__.py
pyMolinfo/docs/chemgraphs.py
pyMolinfo/docs/compound.py
pyMolinfo/docs/compute.py
pyMolinfo/docs/customchemgraph.py
pyMolinfo/docs/element.py
pyMolinfo/docs/graph3d.py
pyMolinfo/docs/molconstructor.py
pyMolinfo/docs/molecule.py
pyMolinfo/docs/molgraph.py
pyMolinfo/docs/molparser.py
pyMolinfo/docs/netwrok.py
pyMolinfo/docs/observer.py
pyMolinfo/docs/structure.py
pyMolinfo/docs/utility.py
pymolinfo-1.8.9.dist-info/LICENSE
pymolinfo-1.8.9.dist-info/METADATA
pymolinfo-1.8.9.dist-info/WHEEL
pymolinfo-1.8.9.dist-info/top_level.txt
pymolinfo-1.8.9.dist-info/RECORD
