Metadata-Version: 2.2
Name: PyMolinfo
Version: 1.8.9
Summary: PyMolinfo provides comprehensive molecular information and analysis.
Author: Sina Gilassi
Author-email: <sina.gilassi@gmail.com>
License: MIT
Keywords: python,chemistry,chemistry-visualization,PyMolinfo,molecular-graph
Classifier: Development Status :: 1 - Planning
Classifier: Intended Audience :: Education
Classifier: Programming Language :: Python :: 3
Classifier: Operating System :: Unix
Classifier: Operating System :: MacOS :: MacOS X
Classifier: Operating System :: Microsoft :: Windows
Requires-Python: >=3.10
License-File: LICENSE
Requires-Dist: pandas
Requires-Dist: pillow
Requires-Dist: requests
Requires-Dist: urllib3
Requires-Dist: matplotlib
Requires-Dist: PubChemQuery
Requires-Dist: numpy
Requires-Dist: plotly
Requires-Dist: networkx
Requires-Dist: PyYAML
Requires-Dist: scipy
Dynamic: author
Dynamic: author-email
Dynamic: classifier
Dynamic: description
Dynamic: description-content-type
Dynamic: keywords
Dynamic: license
Dynamic: requires-dist
Dynamic: requires-python
Dynamic: summary
